mixxx_bisect/__init__.py
mixxx_bisect/__main__.py
mixxx_bisect/options.py
mixxx_bisect/runner/__init__.py
mixxx_bisect/runner/macos.py
mixxx_bisect/runner/windows.py
mixxx_bisect/utils/__init__.py
mixxx_bisect/utils/git.py
mixxx_bisect/utils/request.py
mixxx_bisect/utils/run.py
mixxx_bisect/utils/snapshot.py
venv/bin/rst2html.py
venv/bin/rst2html4.py
venv/bin/rst2html5.py
venv/bin/rst2latex.py
venv/bin/rst2man.py
venv/bin/rst2odt.py
venv/bin/rst2odt_prepstyles.py
venv/bin/rst2pseudoxml.py
venv/bin/rst2s5.py
venv/bin/rst2xetex.py
venv/bin/rst2xml.py
venv/bin/rstpep2html.py
mixxx_bisect-0.1.0.dist-info/LICENSE
mixxx_bisect-0.1.0.dist-info/METADATA
mixxx_bisect-0.1.0.dist-info/WHEEL
mixxx_bisect-0.1.0.dist-info/entry_points.txt
mixxx_bisect-0.1.0.dist-info/top_level.txt
mixxx_bisect-0.1.0.dist-info/RECORD
