Metadata-Version: 2.1
Name: mixxx-bisect
Version: 0.1.0
Summary: Finds Mixxx regressions by binary searching over prebuilt snapshots
License: MIT License
Project-URL: Homepage, https://github.com/fwcd/mixxx-bisect
Project-URL: Repository, https://github.com/fwcd/mixxx-bisect
Keywords: mixxx,bisect,regression
Classifier: Topic :: Utilities
Requires-Python: >=3.9
License-File: LICENSE
Requires-Dist: requests <3,>=2.31
Requires-Dist: beautifulsoup4 <5,>=4.12
Requires-Dist: tqdm <5,>=4.66
